pyui/__init__.py
pyui/cli/main.py
pyui/core/__init__.py
pyui/core/alert.py
pyui/core/component.py
pyui/core/events.py
pyui/core/form.py
pyui/core/grid.py
pyui/core/input.py
pyui/core/layout.py
pyui/core/link.py
pyui/core/modal.py
pyui/core/navbar.py
pyui/core/page.py
pyui/core/router.py
pyui/core/state.py
pyui/core/text.py
pyui/core/theme_toggle.py
pyui/core/toast.py
pyui/core/toast_container.py
pyui/renderer/__init__.py
pyui/renderer/css.py
pyui/renderer/html.py
pyui/renderer/js.py
pyui/renderer/page_renderer.py
pyui_framework-0.1.0.dist-info/METADATA
pyui_framework-0.1.0.dist-info/WHEEL
pyui_framework-0.1.0.dist-info/entry_points.txt
pyui_framework-0.1.0.dist-info/top_level.txt
pyui_framework-0.1.0.dist-info/RECORD
