Metadata-Version: 2.4
Name: pyui-framework
Version: 0.1.0
Summary: A Python-first frontend UI framework
Author: Jyotika Jayani
License: MIT
Keywords: frontend,ui,framework,python
Classifier: Programming Language :: Python :: 3
Classifier: License :: OSI Approved :: MIT License
Classifier: Operating System :: OS Independent
Requires-Python: >=3.9
